wq.start-1.2.1-py3.5-nspkg.pth
wq/start/__init__.py
wq/start/forms.py
wq/start/projects.py
wq/start/version.py
wq/start/django_project/.gitignore
wq/start/django_project/README.md
wq/start/django_project/deploy.sh
wq/start/django_project/runserver.sh
wq/start/django_project/update_json.sh
wq/start/django_project/version.txt
wq/start/django_project/app/.gitignore
wq/start/django_project/app/package.json
wq/start/django_project/app/wq.yml
wq/start/django_project/app/js/README.md
wq/start/django_project/app/js/pginit.js
wq/start/django_project/app/js/project_name.js
wq/start/django_project/app/js/data/.gitignore
wq/start/django_project/app/js/project_name/config.js
wq/start/django_project/app/js/project_name/main.js
wq/start/django_project/app/pgb/config.xml
wq/start/django_project/app/pgb/index-phonegap.html
wq/start/django_project/app/pgb/pginit.js
wq/start/django_project/app/public/favicon.ico
wq/start/django_project/app/public/icon-1024.png
wq/start/django_project/app/public/icon.svg
wq/start/django_project/app/public/index.html
wq/start/django_project/app/public/manifest.json
wq/start/django_project/app/public/robots.txt
wq/start/django_project/app/public/css/project_name.css
wq/start/django_project/app/public/css/project_name/main.css
wq/start/django_project/app/public/css/project_name/responsive.css
wq/start/django_project/app/scss/themes.scss
wq/start/django_project/app/src/README.md
wq/start/django_project/app/src/config.js
wq/start/django_project/app/src/index.js
wq/start/django_project/app/src/serviceWorker.js
wq/start/django_project/app/src/data/.gitignore
wq/start/django_project/conf/project_name.conf
wq/start/django_project/db/manage.py
wq/start/django_project/db/project_name/__init__.py
wq/start/django_project/db/project_name/urls.py
wq/start/django_project/db/project_name/wsgi.py
wq/start/django_project/db/project_name/settings/.gitignore
wq/start/django_project/db/project_name/settings/__init__.py
wq.start-1.2.1.dist-info/LICENSE
wq.start-1.2.1.dist-info/METADATA
wq.start-1.2.1.dist-info/WHEEL
wq.start-1.2.1.dist-info/entry_points.txt
wq.start-1.2.1.dist-info/namespace_packages.txt
wq.start-1.2.1.dist-info/top_level.txt
wq.start-1.2.1.dist-info/RECORD
